{
	"answerText": "Frederic Chopin[10] Chopin [schoe-pan] also wrote several of these pieces that are in three four time, including the \"Minute\". Though these pieces were traditionally used for Austrian dances, Chopin's were meant for concert performances.",
	"prompts": [],
	"heading": "Masonic |2014 | 1 | 9 | Fine Arts | Auditory | HS",
	"subject": "Fine Arts",
	"level": "HS",
	"question": "Question:  [10] Name this 19th century composer who wrote almost all of his works for solo piano, including many etudes [ay-toods], mazurkas, and nocturnes. His etudes have been given nicknames such as Black Keys and Winter Wind.",
	"answers": [
		"Frederic",
		"Chopin",
		"10",
		"schoe-pan",
		"also",
		"wrote",
		"several",
		"these",
		"pieces",
		"that",
		"are",
		"in",
		"three",
		"four",
		"time",
		"including",
		"Minute",
		"Though",
		"were",
		"traditionally",
		"used",
		"for",
		"Austrian",
		"dances",
		"Chopin's",
		"meant",
		"concert",
		"performances"
	]
}