{
	"answerText": "Antonio Vivaldi[10] The Four Seasons is part of this larger collection of twelve violin concertos, which also includes \"La tempesta di mare,\" or \"The Sea Storm.\"",
	"prompts": [],
	"heading": "NASAT  |2014 | 20 | 18 | Fine Arts | Auditory | HS",
	"subject": "Fine Arts",
	"level": "HS",
	"question": "Question: This composer of L'estro armonico gained the nickname \"Red Priest\" after being ordained, and worked at a convent orphanage called the Ospedale della Pieta. For 10 points each:  [10] Name this Italian Baroque composer who composed violin concertos for each time period of his Four Seasons. ",
	"answers": [
		"Antonio",
		"Vivaldi",
		"10",
		"The",
		"Four",
		"Seasons",
		"part",
		"this",
		"larger",
		"collection",
		"twelve",
		"violin",
		"concertos",
		"which",
		"also",
		"includes",
		"La",
		"tempesta",
		"di",
		"mare",
		"Sea",
		"Storm"
	]
}