{
	"answerText": "Maurice Ravel[10] This aforementioned work by Ravel is in a slow 3/4 time with different instruments repeating the main melody, starting with the solo flute followed by the clarinet and bassoon. It features a long, drawn-out crescendo.",
	"prompts": [],
	"heading": "Prison Bowl |2014 | 01 | 15 | Fine Arts | Auditory | HS",
	"subject": "Fine Arts",
	"level": "HS",
	"question": "Question: One of his piano suites titled Miroirs contains movements such as \"Sad Birds\" and \"The Valley of Bells.\" For 10 points each: [10] Name this French Impressionist composer of Concerto for the Left Hand and the ballet Daphnis et Chloe, who notably included a snare drum ostinato in one of his works.",
	"answers": [
		"Maurice",
		"Ravel",
		"10",
		"This",
		"aforementioned",
		"work",
		"by",
		"in",
		"slow",
		"3/4",
		"time",
		"with",
		"different",
		"instruments",
		"repeating",
		"main",
		"melody",
		"starting",
		"solo",
		"flute",
		"followed",
		"clarinet",
		"and",
		"bassoon",
		"It",
		"features",
		"long",
		"drawn-out",
		"crescendo"
	]
}