{
	"answerText": "canon [10] A canon should not be confused with this musical form which uses contrapuntal voices, and, like a sonata, typically has an exposition, a development, and a recapitulation. Bach composed a piece titled after its \"Art.\"",
	"prompts": [],
	"heading": "James |2013 | 10 | 13 | Fine Arts | Auditory | HS",
	"subject": "Fine Arts",
	"level": "HS",
	"question": "Question: There are puzzle, mirror, and table types of this musical form. For 10 points each: [10] Name this musical form similar to a round in which an initial melody is followed by imitators. Pachelbel used this technique for a composition in D.",
	"answers": [
		"canon",
		"10",
		"A",
		"should"
	]
}