{
	"answerText": "Carl Jung[10]  Jung believed that these universal symbols were used to channel human experience and resulted in typical patterns of behavior.",
	"prompts": [],
	"heading": "LIST (Ladue Invitational Spring Tournament) |2012 | LISTIII_Round15.docx | 20 | Social Science |  | HS",
	"subject": "Social Science",
	"level": "HS",
	"question": "Question:  [10]  This psychoanalyst broke with Freud over his assertion that humanity has a collective unconscious. He described the anima and animus as representing the feminine and masculine parts of personality.",
	"answers": [
		"Carl",
		"Jung",
		"10",
		"believed",
		"that",
		"these",
		"universal",
		"symbols",
		"were",
		"used",
		"to",
		"channel",
		"human",
		"experience",
		"and",
		"resulted",
		"in",
		"typical",
		"patterns",
		"behavior"
	]
}