{
	"answerText": "Mojo Jojo (\"mo-jo JO-JO!\")[10]  Mojo Jojo is the main antagonist of this animated TV show broadcast by Cartoon Network. It centers around the superhero trio of Blossom, Bubbles and Buttercup in the city of Townsville.",
	"prompts": [],
	"heading": "Prison Bowl |2013 | Round03.docx | 7 | Trash |  | HS",
	"subject": "Trash",
	"level": "HS",
	"question": "Question:  [10]  Name this purple-caped chimpanzee with green skin and a huge brain. He creates the Rowdyruff Boys to counter his archenemies.",
	"answers": [
		"Mojo",
		"Jojo",
		"mo-jo",
		"JO-JO!",
		"10",
		"main",
		"antagonist",
		"this",
		"animated",
		"TV",
		"show",
		"broadcast",
		"by",
		"Cartoon",
		"Network",
		"It",
		"centers",
		"around",
		"superhero",
		"trio",
		"Blossom",
		"Bubbles",
		"and",
		"Buttercup",
		"in",
		"city",
		"Townsville"
	]
}