{
	"answerText": "Marcus Tullius Cicero[10] This process or property refers to the adjusted amount of space between any two individual characters of a typed phrase. Unlike tracking, it does not refer to the average space between all characters.",
	"prompts": [],
	"heading": "NASAT |2013 | 18 | 12 | Trash | None | College",
	"subject": "Trash",
	"level": "College",
	"question": "Question: Answer these questions about typography, for 10 points each. [10] \"Lorem ipsum,\" a set of junk Latin words used to test a typeface, originates from this Roman orator's On Moral Ends. He also made speeches denouncing Catiline and Marc Antony.",
	"answers": [
		"Marcus",
		"Tullius",
		"Cicero",
		"10",
		"This",
		"process",
		"property",
		"refers",
		"to",
		"adjusted",
		"amount",
		"space",
		"between",
		"two",
		"individual",
		"characters",
		"typed",
		"phrase",
		"Unlike",
		"tracking",
		"does"
	]
}