{
	"answerText": "Liberty Leading the People [or La Liberté guidant le people][10] This contemporary of Eugène Delacroix depicted many scenes from the French Revolution, including one where a man holds a letter to Charlotte Corday. He also depicted Napoleon crossing the alps on horseback.",
	"prompts": [],
	"heading": "Prison Bowl |2014 | 06 | 6 | Fine Arts | Visual | HS",
	"subject": "Fine Arts",
	"level": "HS",
	"question": "Question: Moab [accept Moabites [10] In this Eugène Delacroix painting, the flag-waving title figure wears a Phrygian cap while displaying a bare chest, but not much else.",
	"answers": [
		"Liberty",
		"Leading",
		"People",
		"La",
		"Liberté",
		"guidant",
		"le",
		"people",
		"10",
		"This",
		"contemporary",
		"Eugène",
		"Delacroix",
		"depicted",
		"many",
		"scenes",
		"from",
		"French",
		"Revolution",
		"including",
		"one",
		"where",
		"man",
		"holds",
		"letter",
		"to",
		"Charlotte",
		"Corday",
		"He",
		"also",
		"Napoleon",
		"crossing",
		"alps",
		"horseback"
	]
}