{
	"answerText": "Association of Vineyard Churches [or Vineyard Movement][10] The Vineyard Movement occupies the \"radical middle\" between evangelicalism and this other form of Christianity, which emphasizes spiritual gifts resulting from baptism with the Holy Spirit. It was popularized by the Azusa Street Revival.",
	"prompts": [],
	"heading": "DEES |2014 | Editors 1 | 4 | Religion | None | College",
	"subject": "Religion",
	"level": "College",
	"question": "Question: Tanya Luhrmann studied one church in this movement in When God Talks Back, and an airport church from this movement was the site of the Toronto Blessing.  [10] Name this neo-charismatic Christian movement founded by Kenn Gulliksen and John Wimber, and associated with the \"Signs and Wonders\" movement.",
	"answers": [
		"Association",
		"Vineyard",
		"Churches",
		"Movement",
		"10",
		"The",
		"occupies",
		"radical",
		"middle",
		"between",
		"evangelicalism",
		"and",
		"this",
		"other",
		"form",
		"Christianity",
		"which",
		"emphasizes",
		"spiritual",
		"gifts",
		"resulting",
		"from",
		"baptism",
		"with",
		"Holy",
		"Spirit",
		"It",
		"was",
		"popularized",
		"by",
		"Azusa",
		"Street",
		"Revival"
	]
}