{
	"answerText": "Magnus Carlsen[10] Carlsen also became the youngest ever World Champion, a title once held by this Russian who lost a famous match to Deep Blue and who is now involved in Russian politics.",
	"prompts": [],
	"heading": "ACF Regionals 2014 |2014 | WUSTL-Columbia B-Berkeley A  | 18 | Trash | None | College",
	"subject": "Trash",
	"level": "College",
	"question": "Question:  [10] Name this young Norwegian grandmaster who became World Champion after defeating Viswanathan Anand in 2013.",
	"answers": [
		"Magnus",
		"Carlsen",
		"10",
		"also",
		"became",
		"youngest",
		"ever",
		"World",
		"Champion",
		"title",
		"once",
		"held",
		"by",
		"this",
		"Russian",
		"who",
		"lost",
		"famous",
		"match",
		"to",
		"Deep",
		"Blue",
		"and",
		"now",
		"involved",
		"in",
		"politics"
	]
}