{
	"answerText": "Jake Barnes [or Jake Barnes] [10] Jake visits Pamplona, watches some bull-fighting, and drinks himself into a stupor, all while narrating this Ernest Hemingway novel set in post-World War I Europe.",
	"prompts": [],
	"heading": "NASAT  |2014 | 20 | 15 | Literature | American | HS",
	"subject": "Literature",
	"level": "HS",
	"question": "Question: This character complains that, \"It's awfully easy to be hard-boiled about everything in the daytime, but at night it is another thing.\" For 10 points each: [10] Name this character who, lamenting his impotence, tells Lady Brett Ashley, \"Isn't it pretty to think so?\" at the end of the novel. ",
	"answers": [
		"Jake",
		"Barnes",
		"10",
		"visits",
		"Pamplona",
		"watches",
		"some",
		"bull-fighting",
		"and",
		"drinks",
		"himself",
		"into",
		"stupor",
		"all",
		"while",
		"narrating",
		"this",
		"Ernest",
		"Hemingway",
		"novel",
		"set",
		"in",
		"post-World",
		"War",
		"I",
		"Europe"
	]
}