{
	"answerText": "Corsica [or Corse][10] The Corsican Republic was led by this man, who wrote the Corsican Constitution in Italian. A visit to this man was recounted in James Boswell's An Account of Corsica.",
	"prompts": [],
	"heading": "ACF Regionals  |2015 | Penn A + Louisville + Waterloo B | 5 | History | European | College",
	"subject": "History",
	"level": "College",
	"question": "Question: A German named Theodor von Neuhoff served briefly as a king of this island, and a republic here ended when this island was annexed to France following the Battle of Ponte Novu. For 10 points each: [10] Name this Mediterranean island that formed a Roman province with its southern neighbor. It was the birthplace of Napoleon.",
	"answers": [
		"Corsica",
		"Corse",
		"10",
		"The",
		"Corsican",
		"Republic",
		"was",
		"led",
		"by",
		"this",
		"man",
		"who",
		"wrote",
		"Constitution",
		"in",
		"Italian",
		"A",
		"visit",
		"to",
		"recounted",
		"James",
		"Boswell's",
		"An",
		"Account"
	]
}