{
	"answerText": "Anthony Eden [or Robert Anthony Eden][10] Eden succeeded this man as Prime Minister after having previously been his Foreign Secretary in both the 1940's and 1950's.",
	"prompts": [],
	"heading": "NASAT  |2014 | 5 | 16 | History | British | College",
	"subject": "History",
	"level": "College",
	"question": "Question: In a 2010 survey, this man was ranked the worst postwar British Prime Minister, not even able to defeat Alec Douglas-Home. For 10 points each: [10] Name this man who was Prime Minister during the Suez Crisis and who was also a threetime Foreign Secretary, including during most of World War II.",
	"answers": [
		"Anthony",
		"Eden",
		"Robert",
		"10",
		"succeeded",
		"this",
		"man",
		"as",
		"Prime",
		"Minister",
		"after",
		"having",
		"previously",
		"been",
		"his",
		"Foreign",
		"Secretary",
		"in",
		"both",
		"1940's",
		"and",
		"1950's"
	]
}