{
	"answerText": "Davison threw herself under the king's horse [or anything meaning that she was trampled by a horse such as Anmer fractures her skull][10] Emily Davison and Emmeline Pankhurst were advocates for this civil right for British women. This civil right was partially granted in the last year of the First World War, just in time for the 1918 elections.",
	"prompts": [],
	"heading": "Penn Bowl |2014 | 3 | 1 | History | British | College",
	"subject": "History",
	"level": "College",
	"question": "Question: Recent analysis of film footage suggests that Emily Davison meant to attach a WSPU scarf to a bridle instead of performing this fatal action. For 10 points each: [10] Name this 4 June 1913 action at the Epsom Derby that resulted in Herbert Jones getting concussed and Emily Davison getting killed. Descriptive answers are acceptable.",
	"answers": [
		"Davison",
		"threw",
		"herself",
		"under",
		"king's",
		"horse",
		"anything",
		"meaning",
		"that",
		"she",
		"was",
		"trampled",
		"by",
		"such",
		"as",
		"Anmer",
		"fractures",
		"her",
		"skull",
		"10",
		"Emily",
		"and",
		"Emmeline",
		"Pankhurst",
		"were",
		"advocates",
		"for",
		"this",
		"civil",
		"right",
		"British",
		"women",
		"This",
		"partially",
		"granted",
		"in",
		"last",
		"year",
		"First",
		"World",
		"War",
		"just",
		"time",
		"1918",
		"elections"
	]
}