{
	"answerText": "The House of Vasa [or Vasaätten; or Wazowie][10] This house preceded the Vasa in rule of Sweden. It's union with the Romanov gave it power in Russia, and it was deposed in Greece in 1973. The kings of Denmark rule as a branch of this dynasty.",
	"prompts": [],
	"heading": "ACF Regionals |2013 | Dartmouth A + DCC + VCU A | 2 | History | European | College",
	"subject": "History",
	"level": "College",
	"question": "Question: Identify these exciting Baltic dynasties, for 10 points each: [10] Sigismund III and John II Casimir of Poland were of this house, whose most famous son was Gustavus Adolphus.",
	"answers": [
		"The",
		"House",
		"Vasa",
		"Vasaätten",
		"Wazowie",
		"10",
		"This",
		"house",
		"preceded",
		"in",
		"rule",
		"Sweden",
		"It's",
		"union",
		"with",
		"Romanov",
		"gave",
		"power",
		"Russia",
		"and",
		"was",
		"deposed",
		"Greece",
		"1973",
		"kings",
		"Denmark",
		"as",
		"branch",
		"this",
		"dynasty"
	]
}