{
	"answerText": "Ambrose Burnside[10] Burnside's IX Corps captured what is now called Burnside's Bridge at this battle, the bloodiest day in American history. Lincoln wrote the Emancipation Proclamation shortly after it.",
	"prompts": [],
	"heading": "Dragoon |2013 | 2 | 17 | History | American | College",
	"subject": "History",
	"level": "College",
	"question": "Question: This inaugural president of the NRA surrendered his Rhode Island senate seat to Nelson Aldrich. [10] Name this Union general who was defeated by Robert E. Lee at Fredericksburg.",
	"answers": [
		"Ambrose",
		"Burnside",
		"10",
		"Burnside's",
		"IX",
		"Corps",
		"captured",
		"what",
		"now",
		"called",
		"Bridge",
		"at",
		"this",
		"battle",
		"bloodiest",
		"day",
		"in",
		"American",
		"history",
		"Lincoln",
		"wrote",
		"Emancipation",
		"Proclamation",
		"shortly",
		"after"
	]
}