{
	"answerText": "Eleanor of Aquitaine[10] This abbot helped arrange Eleanor of Aquitaine's first marriage. A patron of Gothic architecture, he rebuilt the Basilica of Saint-Denis.",
	"prompts": [],
	"heading": "Michigan Fall Tournament |2013 | Editors Round 11 | 4 | History | European | College",
	"subject": "History",
	"level": "College",
	"question": "Question: This woman promulgated an early set of maritime laws known as the Rolls of Oleron. For 10 points each: [10] Name this mother of Richard I and wife of both Louis VII and Henry II, a woman from Aquitaine.",
	"answers": [
		"Eleanor",
		"Aquitaine",
		"10",
		"This",
		"abbot",
		"helped",
		"arrange",
		"Aquitaine's",
		"first",
		"marriage",
		"A",
		"patron",
		"Gothic",
		"architecture",
		"he",
		"rebuilt",
		"Basilica",
		"Saint-Denis"
	]
}