{
	"answerText": "delusions [do not accept any other answers][10] Mackay describes the prophecies of this Frenchman, who wrote many quatrains supposedly predicting future events. Despite dying in 1566, this man is still studied by prophecy buffs.",
	"prompts": [],
	"heading": "NASAT |2013 | 8 | 12 | History | European | College",
	"subject": "History",
	"level": "College",
	"question": "Question: The \"national\" and \"philosophical\" types of this state of mind are described in a popular book by Charles Mackay. For 10 points each: [10] Name this type of belief that the title of Mackay's book references as the \"extraordinary popular\" kind. One section of the book describes economic bubbles.",
	"answers": [
		"delusions"
	]
}