{
	"answerText": "Robert Morris [do not accept \"Gouverneur Morris\"][10] Morris was suggested to be the inaugural Secretary of the Treasury, but he turned it down and suggested this man, a leading Federalist, who got the job.",
	"prompts": [],
	"heading": "NASAT |2013 | 9 | 6 | History | American | College",
	"subject": "History",
	"level": "College",
	"question": "Question: This man's namesake \"folly\" was a never-completed mansion designed by Pierre L'Enfant in Philadelphia. For 10 points each: [10] Name this Superintendent of Finance from 1781 to 1784. He was called the \"Financier of the Revolution\" for his loans of money to pay Continental troops.",
	"answers": [
		"Robert",
		"Morris"
	]
}