{
	"answerText": "Askia Mohammad I [or Askia the Great; or Muhammad Toure][10] Judar Pasha led Moroccan forces to victory over the Songhai Empire at this 1591 battle over the salt fields of Tagaza and then sacked the three major Songhai cities, leading to its collapse.",
	"prompts": [],
	"heading": "Penn Bowl |2013 | 1 | 3 | History | World | College",
	"subject": "History",
	"level": "College",
	"question": "Question: After Sunni Ali Ber was swept away by a waterfall, this ruler deposed his young son to take power. For 10 points, [10] Name this ruler whose reign saw the Songhai Empire grow to its greatest height.",
	"answers": [
		"Askia",
		"Mohammad",
		"I",
		"Great",
		"Muhammad",
		"Toure",
		"10",
		"Judar",
		"Pasha",
		"led",
		"Moroccan",
		"forces",
		"to",
		"victory",
		"over",
		"Songhai",
		"Empire",
		"at",
		"this",
		"1591",
		"battle",
		"salt",
		"fields",
		"Tagaza",
		"and",
		"then",
		"sacked",
		"three",
		"major",
		"cities",
		"leading",
		"its",
		"collapse"
	]
}