{
	"answerText": "apartheid[10] Many political dissidents in South Africa were sent to this island prison. Nelson Mandela spent almost 20 years here, and many of those charged in the Rivonia Trial were also sent here.",
	"prompts": [],
	"heading": "Penn Bowl |2013 | 9 | 16 | History | World | College",
	"subject": "History",
	"level": "College",
	"question": "Question: One person who protested against this policy was Steve Biko, who was beaten to death by police, and the terrorist group Spear of the Nation also opposed this policy. [10] Name this policy of racial segregation in South Africa. It led to the creation of Bantustans, which were set aside for black people.",
	"answers": [
		"apartheid",
		"10",
		"Many",
		"political",
		"dissidents",
		"in",
		"South",
		"Africa",
		"were",
		"sent",
		"to",
		"this",
		"island",
		"prison",
		"Nelson",
		"Mandela",
		"spent",
		"almost",
		"20",
		"years",
		"here",
		"and",
		"many",
		"those",
		"charged",
		"Rivonia",
		"Trial",
		"also"
	]
}