{
	"answerText": "Mannerheim Line [or Mannerheim-linja][10] The Mannerheim Line ultimately held during this 19391940 conflict between the Soviet Union and Finland. The Soviet Union attempted to reclaim land lost during its 1917 civil war, but was unable to fully conquer Finland again.",
	"prompts": [],
	"heading": "Terrapin |2013 | Chris Ray - FINAL | 13 | History | European | College",
	"subject": "History",
	"level": "College",
	"question": "Question: Construction on this fortification began after the signing of the Treaty of Tartu in 1920, which established a border between two countries on the Karelian Isthmus. For 10 points each: [10] Name this defensive fortification constructed between Taipale and the Gulf of Finland.",
	"answers": [
		"Mannerheim",
		"Line",
		"Mannerheim-linja",
		"10",
		"The",
		"ultimately",
		"held",
		"during",
		"this",
		"19391940",
		"conflict",
		"between",
		"Soviet",
		"Union",
		"and",
		"Finland",
		"attempted",
		"to",
		"reclaim",
		"land",
		"lost",
		"its",
		"1917",
		"civil",
		"war",
		"but",
		"was",
		"unable",
		"fully",
		"conquer",
		"again"
	]
}