{
	"answerText": "Mercy Otis Warren[10] Abigail Adams wrote that there could be no dispute that \"your Sex\" is \"Naturally Tyrannical\" in a letter to her husband known by this three word phrase that she encourages him to do when designing a Code of Laws.",
	"prompts": [],
	"heading": "VCU Closed |2013 | Michigan B and Yale A | 3 | History | American | College",
	"subject": "History",
	"level": "College",
	"question": "Question: This author satirized the governor of Massachusetts, Thomas Hutchinson, with the character of Rapatio in such plays as The Adulateur and The Group. For 10 points each: [10] Name this woman who wrote a History of the Rise, Progress, and Termination of the American Revolution. She also encouraged her husband to become active in the Committees of Correspondence.",
	"answers": [
		"Mercy",
		"Otis",
		"Warren",
		"10",
		"Abigail",
		"Adams",
		"wrote",
		"that",
		"there",
		"could",
		"be",
		"no",
		"dispute",
		"your",
		"Sex",
		"Naturally",
		"Tyrannical",
		"in",
		"letter",
		"to",
		"her",
		"husband",
		"known",
		"by",
		"this",
		"three",
		"word",
		"phrase",
		"she",
		"encourages",
		"him",
		"when",
		"designing",
		"Code",
		"Laws"
	]
}