{
	"answerText": "Plebs [or Plebeians, or plebeius, plebes][10] This historian, one of the few to write about the secession of the plebs, made it difficult to ascertain what was fact and what was myth about the secessions since he talked about both in his Ab Urbe Condita.",
	"prompts": [],
	"heading": "2012 Penn-ance |2012 | 2 | 7 | History | Classical | College",
	"subject": "History",
	"level": "College",
	"question": "Question: The first secession of this group was on the Mons Sacer while the second took place on the Aventine Hill. For 10 points each: [10] Name this most populous Roman societal class that forced discussion of their rights during the Conflict of the Orders against the Patricians by retreating from the city's public life.",
	"answers": [
		"Plebs",
		"Plebeians",
		"plebeius",
		"plebes",
		"10",
		"This",
		"historian",
		"one",
		"few",
		"to",
		"write",
		"about",
		"secession",
		"plebs",
		"made",
		"difficult",
		"ascertain",
		"what",
		"was",
		"fact",
		"and",
		"myth",
		"secessions",
		"since",
		"he",
		"talked",
		"both",
		"in",
		"his",
		"Ab",
		"Urbe",
		"Condita"
	]
}