{
	"answerText": "John Diefenbaker[10] Diefenbaker led this right-wing party, historically one of two major parties in Canada. It lost a lot of support in the 1990s, and merged with the Canadian Alliance in 2003.",
	"prompts": [],
	"heading": "ACF Regionals |2012 | Alabama + Yale C + Alberta | 15 | History | Other | College",
	"subject": "History",
	"level": "College",
	"question": "Question:  [10] Name this Canadian prime minister who passed the Canadian Bill of Rights in 1960. He cancelled the Avro Arrow project after agreeing to accept Bomarc nuclear missiles from the United States.",
	"answers": [
		"John",
		"Diefenbaker",
		"10",
		"led",
		"this",
		"right-wing",
		"party",
		"historically",
		"one",
		"two",
		"major",
		"parties",
		"in",
		"Canada",
		"It",
		"lost",
		"lot",
		"support",
		"1990s",
		"and",
		"merged",
		"with",
		"Canadian",
		"Alliance",
		"2003"
	]
}