{
	"answerText": "Julius II [accept Giuliano della Rovere][10] The League of Cambrai was formed to combat this \"Most Serene\" Italian republic, which was ruled by \"doges.\" During the Fourth Crusade, Enrico Dandolo, the ruler of this republic, sent crusaders off to siege Constantinople.",
	"prompts": [],
	"heading": "MUT |2012 | 1 | 14 | History | European | College",
	"subject": "History",
	"level": "College",
	"question": "Question: This pontiff is traditionally credited with founding the Corps of the Pontifical Swiss Guard.  [10] Name this pope called the \"Warrior Pope,\" who organized the League of Cambrai with Louis XII and Maximilian I. He was also known for sponsoring such art projects as the painting of the Sistine Chapel's ceiling.",
	"answers": [
		"Julius",
		"II",
		"Giuliano",
		"della",
		"Rovere",
		"10",
		"The",
		"League",
		"Cambrai",
		"was",
		"formed",
		"to",
		"combat",
		"this",
		"Most",
		"Serene",
		"Italian",
		"republic",
		"which",
		"ruled",
		"by",
		"doges",
		"During",
		"Fourth",
		"Crusade",
		"Enrico",
		"Dandolo",
		"ruler",
		"sent",
		"crusaders",
		"off",
		"siege",
		"Constantinople"
	]
}