{
	"answerText": "flood or Great Deluge[10] In Hindusim, this god's son Manu was the progenitor of mankind and had also survived a flood after being forewarned by the fish Shaphari. This god was the creator member of the Trimurti.",
	"prompts": [],
	"heading": "James |2013 | 11 | 15 | Mythology | None | HS",
	"subject": "Mythology",
	"level": "HS",
	"question": "Question: Noah survived one of these events using an ark. For 10 points each: [10] Name these events, one of which Deucalion and Pyrrha survived. Those two later recreated mankind using rocks.",
	"answers": [
		"flood",
		"Great",
		"Deluge",
		"10",
		"In",
		"Hindusim",
		"this",
		"god's",
		"son",
		"Manu",
		"was",
		"progenitor",
		"mankind",
		"and",
		"had",
		"also",
		"survived",
		"after",
		"being",
		"forewarned",
		"by",
		"fish",
		"Shaphari",
		"This",
		"god",
		"creator",
		"member",
		"Trimurti"
	]
}