{
	"answerText": "Ragnarok [or the twilight of the gods] [10] At Ragnarok, Surtr will kill Freyr because the latter gave up his magic sword to this servant so that this man would woo Gerd.",
	"prompts": [],
	"heading": "NASAT  |2014 | 16 | 7 | Mythology | None | College",
	"subject": "Mythology",
	"level": "College",
	"question": "Question: This event will be preceded by the Fimbulwinter and take place on the Vigrid Plain. For 10 points each: [10] Name this event, at which the Norse gods will face off against Surt, Loki, and the monsters under their control. It is the end of the world in Norse mythology. ",
	"answers": [
		"Ragnarok",
		"twilight",
		"gods",
		"10",
		"At",
		"Surtr",
		"will",
		"kill",
		"Freyr",
		"because",
		"latter",
		"gave",
		"up",
		"his",
		"magic",
		"sword",
		"to",
		"this",
		"servant",
		"so",
		"that",
		"man",
		"would",
		"woo",
		"Gerd"
	]
}