{
	"answerText": "Nestor[10] Nestor ruled this city of \"sandy shores\" that Telemachus visits in the Odyssey.",
	"prompts": [],
	"heading": "NASAT |2014 | 3 | 5 | Mythology | None | College",
	"subject": "Mythology",
	"level": "College",
	"question": "Question: In the Iliad, this wise general acts as the chief advisor of the Greeks. [10] Name this hero who became the king of an island after Heracles killed the rest of his family.",
	"answers": [
		"Nestor",
		"10",
		"ruled",
		"this",
		"city",
		"sandy",
		"shores",
		"that",
		"Telemachus",
		"visits",
		"in",
		"Odyssey"
	]
}