{
	"answerText": "Race, Language, and Culture[10] This author of Race, Language, and Culture taught people such as Margaret Mead and Ruth Benedict at Columbia.",
	"prompts": [],
	"heading": "VCU Closed |2013 | Editors 2 | 21 | Social Science | None | College",
	"subject": "Social Science",
	"level": "College",
	"question": "Question: This collection of sixty‐two essays was based on its author's time with the Kwakiutl and includes long decriptions of that group's art and mythology. For 10 points each: [10] Name this 1940 book which also discusses the pros and cons of the \"comparative method\" and aims to prove that its three title phenomena are independent of each other.",
	"answers": [
		"Race",
		"Language",
		"and",
		"Culture",
		"10",
		"This",
		"author",
		"taught",
		"people",
		"such",
		"as",
		"Margaret",
		"Mead",
		"Ruth",
		"Benedict",
		"at",
		"Columbia"
	]
}