{
	"answerText": "syntax[10] The rules of syntax govern parsers which can use various strategies like this one which looks at the input string and guesses small groupings like Det + N = NP which it builds \"up\" at the end to construct a full sentence tree.",
	"prompts": [],
	"heading": "Penn-ance |2012 | 15 | 3 | Social Science | None | College",
	"subject": "Social Science",
	"level": "College",
	"question": "Question: The rules of this field of linguistics specify grammatical relations by identifying the subject, verb, direct object, etc. For 10 points each: [10] Name this subject which concerns the methodology of constructing sentences according to the rules of a grammar, which more generally describes the arrangement of words in a sentence.",
	"answers": [
		"syntax",
		"10",
		"The",
		"rules",
		"govern",
		"parsers",
		"which",
		"can",
		"use",
		"various",
		"strategies",
		"this",
		"one",
		"looks",
		"at",
		"input",
		"string",
		"and",
		"guesses",
		"small",
		"groupings",
		"Det",
		"+",
		"N",
		"=",
		"NP",
		"builds",
		"up",
		"end",
		"to",
		"construct",
		"full",
		"sentence",
		"tree"
	]
}