{
	"answerText": "falsifiability or refutability [accept word forms][10] The criterion of falsifiability was elucidated by this man and later extended by Imre Lakatos. He also criticized the idea that history unwaveringly plays itself out in particular patterns in his The Open Society and its Enemies.",
	"prompts": [],
	"heading": "Penn-ance |2012 | 11 | 11 | Philosophy | None | College",
	"subject": "Philosophy",
	"level": "College",
	"question": "Question: This criterion was used to solve the demarcation problem and the problem of induction by its originator. For 10 points each: [10] Name this important criterion in the philosophy of science, which states that theories should only be held as scientific if there is some way to prove them wrong.",
	"answers": [
		"falsifiability",
		"refutability",
		"word",
		"forms",
		"10",
		"The",
		"criterion",
		"was",
		"elucidated",
		"by",
		"this",
		"man",
		"and",
		"later",
		"extended",
		"Imre",
		"Lakatos",
		"He",
		"also",
		"criticized",
		"idea",
		"that",
		"history",
		"unwaveringly",
		"plays",
		"itself",
		"out",
		"in",
		"particular",
		"patterns",
		"his",
		"Open",
		"Society",
		"its",
		"Enemies"
	]
}