{
	"answerText": "Virginia Woolf[10] This essayist described his favorite mode of transportation in \"The English Mail-Coach\" and Shakespeare's artistic suspension of ordinary human life in \"On the Knocking at the Gate in Macbeth.\"",
	"prompts": [],
	"heading": "NASAT |2013 | 18 | 7 | Literature | British | College",
	"subject": "Literature",
	"level": "College",
	"question": "Question: For 10 points each, name these English essayists. [10] This author ruminated upon her walk through London to buy a pencil in the essay \"Street Haunting,\" though she is better known for her feminist essay A Room of One's Own.",
	"answers": [
		"Virginia",
		"Woolf",
		"10",
		"This",
		"essayist",
		"described",
		"his",
		"favorite",
		"mode",
		"transportation",
		"in",
		"The",
		"English",
		"Mail-Coach",
		"and",
		"Shakespeare's",
		"artistic",
		"suspension",
		"ordinary",
		"human",
		"life",
		"On",
		"Knocking",
		"at",
		"Gate",
		"Macbeth"
	]
}