{
	"answerText": "Beatrice[10] Luckily, the couples of Claudio and Hero, and Benedick and Beatrice, end up together at the end of the Shakespeare play set in Messina.",
	"prompts": [],
	"heading": "VCU Closed |2013 | Georgia Tech and Williams | 5 | Literature | British | College",
	"subject": "Literature",
	"level": "College",
	"question": "Question: This character claims, \"A bird of my tongue is better than a beast of yours\" and declares she will not run mad until a \"hot January.\" For 10 points each: [10] Name this character who engages in a \"merry war\" of wits. She later insists that Claudio must be killed for the insult he has given to her friend Hero.",
	"answers": [
		"Beatrice",
		"10",
		"Luckily",
		"couples",
		"Claudio",
		"and",
		"Hero",
		"Benedick",
		"end",
		"up",
		"together",
		"at",
		"Shakespeare",
		"play",
		"set",
		"in",
		"Messina"
	]
}