{
	"answerText": "strings[10] The AdS-CFT correspondence is often used to study the quantum theory of this force. Another theory of it was posited by Einstein in general relativity, but the most famous theory of it was posited by Newton.",
	"prompts": [],
	"heading": "Missiles of October |2011 | 7 | 16 | Science | Physics | College",
	"subject": "Science",
	"level": "College",
	"question": "Question: The AdS-CFT correspondence says there is a duality between a theory based on these in AdS space and a quantum field theory on the boundary that has a lower dimension. For 10 points each: [10] Name these objects whose higher dimensional equivalents are called p-branes.",
	"answers": [
		"strings",
		"10",
		"The",
		"AdS-CFT",
		"correspondence",
		"often",
		"used",
		"to",
		"study",
		"quantum",
		"theory",
		"this",
		"force"
	]
}