{
	"answerText": "Viracocha [Prompt on Kon-Tiki][10] Inti was the deity of this celestial body. Viracocha created time by telling him to move around the sky, and the Inti Raymi is held when this entity is closest to the Earth.",
	"prompts": [
		"Kon-Tiki",
		"10",
		"Inti",
		"was",
		"deity",
		"this",
		"celestial",
		"body",
		"Viracocha",
		"created",
		"time",
		"by",
		"telling",
		"him",
		"to",
		"move",
		"around",
		"sky",
		"and",
		"Inti",
		"Raymi",
		"held",
		"when",
		"this",
		"entity",
		"closest",
		"to",
		"Earth"
	],
	"heading": "DRAGOON |2013 | 12 | 9 | Mythology | None | College",
	"subject": "Mythology",
	"level": "College",
	"question": "Question: One story states that after this god created the first set of humans from stones, he didn't like how big and stupid they were so he destroyed them with a flood and made better humans. For 10 points each: [10] Name this creator god of Incan myth, who was the father of Inti and Mama Quilla.",
	"answers": [
		"Viracocha"
	]
}