{
	"answerText": "string searching [accept string matching, substring searching, or equivalents][10] The RabinKarp algorithm uses a \"rolling\" one of these constructs. These constructs map an arbitrary number of input keys onto a fixed number of \"buckets.\"",
	"prompts": [],
	"heading": "STIMPY |2015 | Editors 1 | 10 | Science | Computer Science | College",
	"subject": "Science",
	"level": "College",
	"question": "Question: The KnuthMorrisPratt algorithm constructs a deterministic finite automaton to perform this task. For 10 points each: [10] Name this action also performed by the RabinKarp randomized fingerprint algorithm and the BoyerMoore algorithm.",
	"answers": [
		"string",
		"searching",
		"matching",
		"substring",
		"equivalents",
		"10",
		"The",
		"RabinKarp",
		"algorithm",
		"uses",
		"rolling",
		"one",
		"these",
		"constructs",
		"These",
		"map",
		"an",
		"arbitrary",
		"number",
		"input",
		"keys",
		"onto",
		"fixed",
		"buckets"
	]
}