{
	"answerText": "resonance[10] Resonance typically occurs when this parameter is significantly less than one. It is typically represented by zeta.",
	"prompts": [],
	"heading": "NASAT  |2014 | 4 | 17 | Science | Physics | College",
	"subject": "Science",
	"level": "College",
	"question": "Question: Tuned mass dampers are a way of cutting down on this effect, and this effect being driven by a vortex street was responsible for the Tacoma Narrows Bridge disaster. For 10 points each:  [10] Name this phenomenon that occurs when a system is driven periodically at its natural frequency. It occurs at normal modes. ",
	"answers": [
		"resonance",
		"10",
		"Resonance",
		"typically",
		"occurs",
		"when",
		"this",
		"parameter",
		"significantly",
		"less",
		"than",
		"one",
		"It",
		"represented",
		"by",
		"zeta"
	]
}