{
	"answerText": "major hurricane [or tropical cyclone; or typhoon; prompt on cyclonic storm][10] Maloney and Hartmann theorized that this dominant component of the intraseasonal variability modulates tropical cyclone activity. It propagates from the Indian Ocean and western Pacific Ocean to the eastern Pacific Ocean over a 30 to 60 day period.",
	"prompts": [
		"cyclonic",
		"storm",
		"10",
		"Maloney",
		"and",
		"Hartmann",
		"theorized",
		"that",
		"this",
		"dominant",
		"component",
		"intraseasonal",
		"variability",
		"modulates",
		"tropical",
		"cyclone",
		"activity",
		"It",
		"propagates",
		"from",
		"Indian",
		"Ocean",
		"and",
		"western",
		"Pacific",
		"Ocean",
		"to",
		"eastern",
		"Pacific",
		"Ocean",
		"over",
		"30",
		"to",
		"60",
		"day",
		"period"
	],
	"heading": "ACF Regionals |2013 | Rice A + Columbia A | 14 | Science | Other | College",
	"subject": "Science",
	"level": "College",
	"question": "Question: The strength of these storm systems is measured on the Saffir-Simpson scale. For 10 points each, [10] Identify this storm system with maximum sustained wind speeds of 74 miles per hour or higher, a step up from tropical storms.",
	"answers": [
		"major",
		"hurricane",
		"tropical",
		"cyclone",
		"typhoon"
	]
}