{
	"answerText": "Heracles [or Hercules][10] Augeas's daughter Agamede copulated with this god to give birth to Actor, Belus, and Dictys. This god changed Caeneus to a male after raping her.",
	"prompts": [],
	"heading": "Penn Bowl |2014 | 11 | 1 | Mythology | None | College",
	"subject": "Mythology",
	"level": "College",
	"question": "Question: Answer some questions about the cleaning of the Augean stables, for 10 points each: [10] The cleaning of the Augean stables was the fifth of this hero's 12 labors, which were presided over by his cowardly cousin Eurystheus.",
	"answers": [
		"Heracles",
		"Hercules",
		"10",
		"Augeas's",
		"daughter",
		"Agamede",
		"copulated",
		"with",
		"this",
		"god",
		"to",
		"give",
		"birth",
		"Actor",
		"Belus",
		"and",
		"Dictys",
		"This",
		"changed",
		"Caeneus",
		"male",
		"after",
		"raping",
		"her"
	]
}