{
	"answerText": "Videodrome[10] This Canadian director of Videodrome also directed a film about diseased organic game consoles called Existenz. He also directed Scanners, a remake of The Fly, and Eastern Promises.",
	"prompts": [],
	"heading": "Penn Bowl |2014 | 6 | 6 | Trash | None | College",
	"subject": "Trash",
	"level": "College",
	"question": "Question: In a notable scene from this film, the protagonist hallucinates that his torso contains a VCR. For 10 points each: [10] Name this horror film in which Max Renn discovers a broadcast of people being tortured and killed in an orange room. The broadcast actually causes brain tumors.",
	"answers": [
		"Videodrome",
		"10",
		"This",
		"Canadian",
		"director",
		"also",
		"directed",
		"film",
		"about",
		"diseased",
		"organic",
		"game",
		"consoles",
		"called",
		"Existenz",
		"He",
		"Scanners",
		"remake",
		"The",
		"Fly",
		"and",
		"Eastern",
		"Promises"
	]
}